<?xml version="1.0"?>
<page type="infoWithPopupButton" zone="-1">


	<header><![CDATA[<span id="welcome">Welcome to the </span><span id="title1">Operations</span><br/><span id="title2"> and </span><br/><span id="title3">Management</span> <span id="title4">module</span>]]></header>
	<body><![CDATA[ <p>The main Different Between a Leader and a Manager is that the former have followers and the latter have people who work under them.The main Different Between a Leader and a Manager is that the former have followers and the latter have people who work under them.The main Different Between a Leader and a Manager is that the former have followers and the latter have people who work under them.</p>
	
	
	<p>Managers need to understand interdependecy of Department, partnership allainces and team across the organisation.Managers need to understand interdependecy of Department, partnership allainces and team across the organisation.Managers need to understand interdependecy of Department, partnership allainces and team across the organisation.</p>]]></body>
	
	
	<popupButton pageId="popup1">More About Excell Services</popupButton>
	

	<iText><![CDATA[Select Continue to proceed.]]></iText>
	<nextButton pageId="page1"><![CDATA[Continue]]></nextButton>


</page>